blurface/__init__.py
blurface/__main__.py
blurface/utils.py
blurface-0.1.0.dist-info/METADATA
blurface-0.1.0.dist-info/WHEEL
blurface-0.1.0.dist-info/entry_points.txt
blurface-0.1.0.dist-info/top_level.txt
blurface-0.1.0.dist-info/RECORD
