Metadata-Version: 2.2
Name: blurface
Version: 0.1.0
Summary: A command-line tool to blur human faces in MP4 videos using face detection.
Home-page: https://github.com/Ezharjan/blurface
Author: Alexander Ezharjan
Author-email: mysoft@111.com
License: MIT
Classifier: Programming Language :: Python :: 3
Classifier: License :: OSI Approved :: MIT License
Classifier: Operating System :: OS Independent
Requires-Python: >=3.9
Requires-Dist: retina-face==0.0.17
Requires-Dist: tensorflow>=2.10.0
Requires-Dist: tf-keras>=2.19.0
Requires-Dist: tqdm>=4.60.0
Requires-Dist: torch<2.5.0,>=1.9.0
Requires-Dist: ffmpeg-python>=0.2.0
Dynamic: author
Dynamic: author-email
Dynamic: classifier
Dynamic: description
Dynamic: description-content-type
Dynamic: home-page
Dynamic: license
Dynamic: requires-dist
Dynamic: requires-python
Dynamic: summary
